mcp_aws_level_checker/__init__.py
mcp_aws_level_checker/__main__.py
mcp_aws_level_checker/server.py
mcp_aws_level_checker-0.1.1.dist-info/METADATA
mcp_aws_level_checker-0.1.1.dist-info/WHEEL
mcp_aws_level_checker-0.1.1.dist-info/entry_points.txt
mcp_aws_level_checker-0.1.1.dist-info/licenses/LICENSE
mcp_aws_level_checker-0.1.1.dist-info/RECORD
