Metadata-Version: 2.4
Name: mcp-aws-level-checker
Version: 0.1.1
Summary: AWS技術ブログのレベルを分析するMCPサーバー
Project-URL: Homepage, https://github.com/yourusername/mcp-aws-level-checker
Project-URL: Bug Tracker, https://github.com/yourusername/mcp-aws-level-checker/issues
Author-email: Your Name <your.email@example.com>
License: MIT License
License-File: LICENSE
Classifier: License :: OSI Approved :: MIT License
Classifier: Operating System :: OS Independent
Classifier: Programming Language :: Python :: 3
Requires-Python: >=3.9
Requires-Dist: mcp[cli]>=1.2.0
